gTTS_token-1.1.2.dist-info/METADATA
gTTS_token-1.1.2.dist-info/RECORD
gTTS_token-1.1.2.dist-info/WHEEL
gTTS_token-1.1.2.dist-info/top_level.txt
gtts_token/__init__.py
gtts_token/gtts_token.py
gtts_token/version.py
