Metadata-Version: 1.1
Name: gTTS-token
Version: 1.1.2
Summary: Calculates a token to run the Google Translate text to speech
Home-page: https://github.com/boudewijn26/gTTS-token
Author: Boudewijn van Groos
Author-email: boudewijn@vangroos.nl
License: MIT
Platform: UNKNOWN
Classifier: Environment :: Console
Classifier: Intended Audience :: Developers
Classifier: License :: OSI Approved :: MIT License
Classifier: Operating System :: MacOS :: MacOS X
Classifier: Operating System :: Unix
Classifier: Operating System :: POSIX
Classifier: Operating System :: POSIX :: Linux
Classifier: Programming Language :: Python :: 2.7
Classifier: Programming Language :: Python :: 3.3
Classifier: Programming Language :: Python :: 3.4
Classifier: Topic :: Software Development :: Libraries
Classifier: Topic :: Multimedia :: Sound/Audio :: Speech
